[
    {
        "title": "掘金vs湖人",
        "href": "https://www.douyin.com/hot/2034875",
        "create_time": 1742440307014
    },
    {
        "title": "国足对战沙特主裁判确认",
        "href": "https://www.douyin.com/hot/2034362",
        "create_time": 1742440307014
    },
    {
        "title": "增收减负 今年提振消费这么干",
        "href": "https://www.douyin.com/hot/2034645",
        "create_time": 1742440307014
    },
    {
        "title": "春分吃什么",
        "href": "https://www.douyin.com/hot/2034464",
        "create_time": 1742440307014
    },
    {
        "title": "全运会乒乓球团体赛资格赛分组",
        "href": "https://www.douyin.com/hot/2034001",
        "create_time": 1742440307014
    },
    {
        "title": "专家：胡塞击中美航母概率并非是零",
        "href": "https://www.douyin.com/hot/2034506",
        "create_time": 1742440307015
    },
    {
        "title": "王大雷：国足出线需脚踏实地",
        "href": "https://www.douyin.com/hot/2034277",
        "create_time": 1742440307015
    },
    {
        "title": "国足18强赛破茧之路",
        "href": "https://www.douyin.com/hot/2034664",
        "create_time": 1742440307015
    },
    {
        "title": "饶毅将赴福耀科技大学系谣言",
        "href": "https://www.douyin.com/hot/2034961",
        "create_time": 1742440307015
    },
    {
        "title": "春分文案",
        "href": "https://www.douyin.com/hot/2034763",
        "create_time": 1742440307015
    },
    {
        "title": "特朗普为何急于解密肯尼迪档案",
        "href": "https://www.douyin.com/hot/2034503",
        "create_time": 1742440307015
    },
    {
        "title": "百度通报“副总裁女儿开盒”事件",
        "href": "https://www.douyin.com/hot/2034484",
        "create_time": 1742440307015
    },
    {
        "title": "马斯克财富净值缩水超1000亿美元",
        "href": "https://www.douyin.com/hot/2034683",
        "create_time": 1742440307015
    },
    {
        "title": "哪吒汽车辟谣解散研发团队",
        "href": "https://www.douyin.com/hot/2033875",
        "create_time": 1742440307015
    },
    {
        "title": "百度高管女儿开盒如何追责",
        "href": "https://www.douyin.com/hot/2034634",
        "create_time": 1742440307015
    },
    {
        "title": "什么叫开盒",
        "href": "https://www.douyin.com/hot/2033815",
        "create_time": 1742440307015
    },
    {
        "title": "美联储按兵不动 美股集体收涨",
        "href": "https://www.douyin.com/hot/2034700",
        "create_time": 1742440307015
    },
    {
        "title": "整治和铲除开盒挂人刻不容缓",
        "href": "https://www.douyin.com/hot/2033681",
        "create_time": 1742440307015
    },
    {
        "title": "媒体：休假羞耻该成过去式了",
        "href": "https://www.douyin.com/hot/2033535",
        "create_time": 1742440307015
    },
    {
        "title": "小米SU7 Ultra续航测试",
        "href": "https://www.douyin.com/hot/2032789",
        "create_time": 1742440307015
    },
    {
        "title": "土耳其金融市场异动",
        "href": "https://www.douyin.com/hot/2034210",
        "create_time": 1742440307015
    },
    {
        "title": "泽连斯基与特朗普通电话",
        "href": "https://www.douyin.com/hot/2034682",
        "create_time": 1742440307015
    },
    {
        "title": "雁回时女主救赎小时候的自己",
        "href": "https://www.douyin.com/hot/2033972",
        "create_time": 1742440307015
    },
    {
        "title": "嘘国王在冬眠花瓣雨拥抱挑战",
        "href": "https://www.douyin.com/hot/2034667",
        "create_time": 1742440307015
    },
    {
        "title": "陈都灵新剧崩溃哭诉母亲",
        "href": "https://www.douyin.com/hot/2034033",
        "create_time": 1742440307015
    },
    {
        "title": "特雷伯克入驻抖音",
        "href": "https://www.douyin.com/hot/2033359",
        "create_time": 1742440307015
    },
    {
        "title": "庞麦郎巡演上海站门票售罄",
        "href": "https://www.douyin.com/hot/2034147",
        "create_time": 1742440307015
    },
    {
        "title": "我说普通话方言版",
        "href": "https://www.douyin.com/hot/2033941",
        "create_time": 1742440307015
    },
    {
        "title": "俄称完成“175对175”战俘交换",
        "href": "https://www.douyin.com/hot/2034626",
        "create_time": 1742440307015
    },
    {
        "title": "金秀贤又掉代言了",
        "href": "https://www.douyin.com/hot/2033837",
        "create_time": 1742440307015
    },
    {
        "title": "乘风2025官宣",
        "href": "https://www.douyin.com/hot/2033868",
        "create_time": 1742440307015
    },
    {
        "title": "努力备战广西三月三",
        "href": "https://www.douyin.com/hot/2033687",
        "create_time": 1742440307015
    },
    {
        "title": "把蜜雪冰城拍成喝不起的样子",
        "href": "https://www.douyin.com/hot/2033648",
        "create_time": 1742440307015
    },
    {
        "title": "反复播放边伯贤随舞",
        "href": "https://www.douyin.com/hot/2034457",
        "create_time": 1742440307015
    },
    {
        "title": "雁回时野狐与蟒蛇的对峙",
        "href": "https://www.douyin.com/hot/2034176",
        "create_time": 1742440307015
    },
    {
        "title": "素颜你还会爱我吗",
        "href": "https://www.douyin.com/hot/2034149",
        "create_time": 1742440307015
    },
    {
        "title": "李敏镐时隔9年来上海",
        "href": "https://www.douyin.com/hot/2034607",
        "create_time": 1742440307015
    },
    {
        "title": "杜克和孟加拉一哥的故事",
        "href": "https://www.douyin.com/hot/2033861",
        "create_time": 1742440307015
    },
    {
        "title": "春分到了别再睡懒觉了",
        "href": "https://www.douyin.com/hot/2034702",
        "create_time": 1742440307015
    },
    {
        "title": "来一口乡间春分的味道",
        "href": "https://www.douyin.com/hot/2034541",
        "create_time": 1742440307015
    },
    {
        "title": "我在抖音也是有娃的人了",
        "href": "https://www.douyin.com/hot/2034416",
        "create_time": 1742440307015
    },
    {
        "title": "周杰伦9月在山东开唱",
        "href": "https://www.douyin.com/hot/2034220",
        "create_time": 1742440307015
    },
    {
        "title": "春分立蛋",
        "href": "https://www.douyin.com/hot/2034677",
        "create_time": 1742440307015
    },
    {
        "title": "起猛了在学校看见“海盗”了",
        "href": "https://www.douyin.com/hot/2034351",
        "create_time": 1742440307015
    },
    {
        "title": "贺峻霖出国旅游向太说全包",
        "href": "https://www.douyin.com/hot/2034188",
        "create_time": 1742440307015
    },
    {
        "title": "香港街头偶遇梁朝伟",
        "href": "https://www.douyin.com/hot/2034608",
        "create_time": 1742440307015
    },
    {
        "title": "来到了天津卫",
        "href": "https://www.douyin.com/hot/2034153",
        "create_time": 1742440307015
    },
    {
        "title": "各地文旅开启回答我",
        "href": "https://www.douyin.com/hot/2033245",
        "create_time": 1742440307015
    },
    {
        "title": "一口气看浪姐30位姐姐全介绍",
        "href": "https://www.douyin.com/hot/2034661",
        "create_time": 1742440307015
    },
    {
        "title": "今日春分",
        "href": "https://www.douyin.com/hot/2034701",
        "create_time": 1742447632325
    },
    {
        "title": "家电维修界的华佗",
        "href": "https://www.douyin.com/hot/2033962",
        "create_time": 1742447632325
    },
    {
        "title": "张宏森任中国作协主席",
        "href": "https://www.douyin.com/hot/2034987",
        "create_time": 1742447632325
    },
    {
        "title": "雁回时母女互为托举",
        "href": "https://www.douyin.com/hot/2034966",
        "create_time": 1742447632325
    },
    {
        "title": "李嘉诚甩卖港口意味着什么",
        "href": "https://www.douyin.com/hot/2035031",
        "create_time": 1742447632325
    },
    {
        "title": "小米SU7 Ultra能赢法拉利吗",
        "href": "https://www.douyin.com/hot/2034946",
        "create_time": 1742447632325
    },
    {
        "title": "马龙王楚钦全运会资格赛训练",
        "href": "https://www.douyin.com/hot/2034297",
        "create_time": 1742447632325
    },
    {
        "title": "国足进行踩场训练",
        "href": "https://www.douyin.com/hot/2034983",
        "create_time": 1742447632325
    },
    {
        "title": "欧豪教白鹿扇自己耳光",
        "href": "https://www.douyin.com/hot/2035033",
        "create_time": 1742447632325
    },
    {
        "title": "姐姐进行曲",
        "href": "https://www.douyin.com/hot/2034981",
        "create_time": 1742447632325
    },
    {
        "title": "美联储一小时提16次不确定",
        "href": "https://www.douyin.com/hot/2034814",
        "create_time": 1742447632325
    },
    {
        "title": "马龙王楚钦男双开门红",
        "href": "https://www.douyin.com/hot/2034889",
        "create_time": 1742447632325
    },
    {
        "title": "虞书欣何与双轨海南杀青",
        "href": "https://www.douyin.com/hot/2034970",
        "create_time": 1742447632325
    },
    {
        "title": "电影我会好好的终极预告好哭",
        "href": "https://www.douyin.com/hot/2034992",
        "create_time": 1742447632325
    },
    {
        "title": "王大雷：这是最团结的中国队",
        "href": "https://www.douyin.com/hot/2034954",
        "create_time": 1742447632325
    },
    {
        "title": "00后拒绝“请假羞耻症”",
        "href": "https://www.douyin.com/hot/2034372",
        "create_time": 1742447632325
    },
    {
        "title": "买肠粉咋还送饮料啊",
        "href": "https://www.douyin.com/hot/2034490",
        "create_time": 1742447632325
    },
    {
        "title": "你只管向春天走去",
        "href": "https://www.douyin.com/hot/2033820",
        "create_time": 1742451572124
    },
    {
        "title": "湖人120:108战胜掘金",
        "href": "https://www.douyin.com/hot/2034875",
        "create_time": 1742451572124
    },
    {
        "title": "刘亦菲的男主们送来获奖祝福",
        "href": "https://www.douyin.com/hot/2034818",
        "create_time": 1742451572124
    },
    {
        "title": "湖北大学失联女大学生家属发声",
        "href": "https://www.douyin.com/hot/2034943",
        "create_time": 1742451572124
    },
    {
        "title": "警惕隐形肥胖",
        "href": "https://www.douyin.com/hot/2033903",
        "create_time": 1742451572124
    },
    {
        "title": "黄雀郭鹏飞怀疑黎小莲",
        "href": "https://www.douyin.com/hot/2034991",
        "create_time": 1742451572124
    },
    {
        "title": "普京：将彻底击败库尔斯克乌军",
        "href": "https://www.douyin.com/hot/2034808",
        "create_time": 1742451572124
    },
    {
        "title": "名嘴大咖为国足支招",
        "href": "https://www.douyin.com/hot/2035223",
        "create_time": 1742454820349
    },
    {
        "title": "全广西集体同意三月三放假",
        "href": "https://www.douyin.com/hot/2034036",
        "create_time": 1742454820349
    },
    {
        "title": "余承东直播华为新品发布会",
        "href": "https://www.douyin.com/hot/2035178",
        "create_time": 1742454820349
    },
    {
        "title": "边伯贤点赞张家界文旅",
        "href": "https://www.douyin.com/hot/2035243",
        "create_time": 1742454820349
    },
    {
        "title": "雁回时女本位视角",
        "href": "https://www.douyin.com/hot/2034744",
        "create_time": 1742454820349
    },
    {
        "title": "侯佩岑入驻抖音",
        "href": "https://www.douyin.com/hot/2034996",
        "create_time": 1742454820349
    },
    {
        "title": "3月LPR报价出炉",
        "href": "https://www.douyin.com/hot/2034813",
        "create_time": 1742454820349
    },
    {
        "title": "技术流自带bgm",
        "href": "https://www.douyin.com/hot/2034584",
        "create_time": 1742454820349
    },
    {
        "title": "谁懂春分花神妆的含金量",
        "href": "https://www.douyin.com/hot/2034881",
        "create_time": 1742454820349
    },
    {
        "title": "全球首款阔折叠华为PuraX",
        "href": "https://www.douyin.com/hot/2035300",
        "create_time": 1742458702762
    },
    {
        "title": "湖北大学失联女生家属发声",
        "href": "https://www.douyin.com/hot/2034943",
        "create_time": 1742458702762
    },
    {
        "title": "华为新品发布会",
        "href": "https://www.douyin.com/hot/2035178",
        "create_time": 1742458702762
    },
    {
        "title": "技术流自带BGM",
        "href": "https://www.douyin.com/hot/2034584",
        "create_time": 1742458702763
    },
    {
        "title": "马龙3:1战胜谢聪凡",
        "href": "https://www.douyin.com/hot/2035056",
        "create_time": 1742458702763
    },
    {
        "title": "国际幸福日",
        "href": "https://www.douyin.com/hot/2034722",
        "create_time": 1742458702763
    },
    {
        "title": "拯救地球之前把这片田先浇完",
        "href": "https://www.douyin.com/hot/2034792",
        "create_time": 1742458702763
    },
    {
        "title": "韩国国会通过“金建希常设特检案”",
        "href": "https://www.douyin.com/hot/2035451",
        "create_time": 1742462119874
    },
    {
        "title": "华为阔折叠Pura X",
        "href": "https://www.douyin.com/hot/2035300",
        "create_time": 1742462119874
    },
    {
        "title": "Pura X起售价7499元",
        "href": "https://www.douyin.com/hot/2035360",
        "create_time": 1742462119874
    },
    {
        "title": "河南项城一工厂突发爆炸",
        "href": "https://www.douyin.com/hot/2035304",
        "create_time": 1742462119874
    },
    {
        "title": "刘晓庆谈婚恋观：不能随便结婚",
        "href": "https://www.douyin.com/hot/2035089",
        "create_time": 1742462119874
    },
    {
        "title": "男人结婚时能做出哪些离谱操作",
        "href": "https://www.douyin.com/hot/2035283",
        "create_time": 1742462119874
    },
    {
        "title": "《刺客信条:影》评测",
        "href": "https://www.douyin.com/hot/2033616",
        "create_time": 1742462119874
    },
    {
        "title": "水饺皇后定档",
        "href": "https://www.douyin.com/hot/2034979",
        "create_time": 1742462119874
    },
    {
        "title": "美国打着关税战还想要鸡蛋",
        "href": "https://www.douyin.com/hot/2035317",
        "create_time": 1742462119874
    }
]